[
     {
          "Name": "Nathan Coulter-Nile",
          "Runs": "1",
          "Fours": "0",
          "Sixes": "0",
          "Strike Rate": "33.33",
          "Date": " Nov 3 2020",
          "Venue": " Sharjah",
          "Opponent Team": "Sunrisers Hyderabad",
          "Result": "Sunrisers won by 10 wickets (with 17 balls remaining)"
     }
][
     {
          "Name": "Nathan Coulter-Nile",
          "Runs": "24",
          "Fours": "4",
          "Sixes": "0",
          "Strike Rate": "200.00",
          "Date": " Oct 18 2020",
          "Venue": " Dubai",
          "Opponent Team": "Kings XI Punjab",
          "Result": "Match tied (Kings XI won the one-over eliminator)"
     }
]